zp3/__init__.py
zp3-2.0.0.9.dist-info/WHEEL
zp3-2.0.0.9.dist-info/METADATA
zp3-2.0.0.9.dist-info/RECORD
